{
    "scene_name": "cornell_box_tall-box",
    "version": "1.0",
    "objects": {
        "background_0": {
            "mesh_path": "/home/devel/.draft/renderformer/examples/templates/backgrounds/plane.obj",
            "transform": {
                "translation": [
                    0.0,
                    0.0,
                    0.0
                ],
                "rotation": [
                    0.0,
                    0.0,
                    0.0
                ],
                "scale": [
                    0.5,
                    0.5,
                    0.5
                ],
                "normalize": false
            },
            "material": {
                "diffuse": [
                    0.4,
                    0.4,
                    0.4
                ],
                "specular": [
                    0.01,
                    0.01,
                    0.01
                ],
                "random_diffuse_max": 0.4,
                "roughness": 0.99,
                "emissive": [
                    0.0,
                    0.0,
                    0.0
                ],
                "smooth_shading": true,
                "rand_tri_diffuse_seed": null
            }
        },
        "background_1": {
            "mesh_path": "/home/devel/.draft/renderformer/examples/templates/backgrounds/wall0.obj",
            "transform": {
                "translation": [
                    0.0,
                    0.0,
                    0.0
                ],
                "rotation": [
                    0.0,
                    0.0,
                    0.0
                ],
                "scale": [
                    0.5,
                    0.5,
                    0.5
                ],
                "normalize": false
            },
            "material": {
                "diffuse": [
                    0.4,
                    0.4,
                    0.4
                ],
                "specular": [
                    0.55,
                    0.55,
                    0.55
                ],
                "random_diffuse_max": 0.4,
                "roughness": 0.1,
                "emissive": [
                    0.0,
                    0.0,
                    0.0
                ],
                "smooth_shading": true,
                "rand_tri_diffuse_seed": null
            }
        },
        "background_2": {
            "mesh_path": "/home/devel/.draft/renderformer/examples/templates/backgrounds/wall1.obj",
            "transform": {
                "translation": [
                    0.0,
                    0.0,
                    0.0
                ],
                "rotation": [
                    0.0,
                    0.0,
                    0.0
                ],
                "scale": [
                    0.5,
                    0.5,
                    0.5
                ],
                "normalize": false
            },
            "material": {
                "diffuse": [
                    0.11390590873562889,
                    0.8584516535522408,
                    0.019029412426741887
                ],
                "specular": [
                    0.01,
                    0.01,
                    0.01
                ],
                "random_diffuse_max": 0.5,
                "roughness": 0.99,
                "emissive": [
                    0.0,
                    0.0,
                    0.0
                ],
                "smooth_shading": true,
                "rand_tri_diffuse_seed": null
            }
        },
        "background_3": {
            "mesh_path": "/home/devel/.draft/renderformer/examples/templates/backgrounds/wall2.obj",
            "transform": {
                "translation": [
                    0.0,
                    0.0,
                    0.0
                ],
                "rotation": [
                    0.0,
                    0.0,
                    0.0
                ],
                "scale": [
                    0.5,
                    0.5,
                    0.5
                ],
                "normalize": false
            },
            "material": {
                "diffuse": [
                    0.7679293659697277,
                    0.2938554718164961,
                    0.040702814542072974
                ],
                "specular": [
                    0.01,
                    0.01,
                    0.01
                ],
                "random_diffuse_max": 0.5,
                "roughness": 0.99,
                "emissive": [
                    0.0,
                    0.0,
                    0.0
                ],
                "smooth_shading": false,
                "rand_tri_diffuse_seed": null
            }
        },
        "tall-box": {
            "mesh_path": "/home/devel/.draft/renderformer/examples/objects/cbox/tall-box.obj",
            "transform": {
                "translation": [
                    0.0,
                    0.0,
                    0.0
                ],
                "rotation": [
                    0.0,
                    0.0,
                    0.0
                ],
                "scale": [
                    1.1659084609384047,
                    1.1659084609384047,
                    1.1659084609384047
                ],
                "normalize": true
            },
            "material": {
                "diffuse": [
                    0.0244347474774132,
                    0.24900105925681304,
                    0.17921199860107953
                ],
                "specular": [
                    0.6566430520276075,
                    0.31870167712984,
                    0.634142067925398
                ],
                "random_diffuse_max": 0.21190711988945055,
                "roughness": 0.21537395692514238,
                "emissive": [
                    0.0,
                    0.0,
                    0.0
                ],
                "smooth_shading": false,
                "rand_tri_diffuse_seed": null
            }
        },
        "light_0": {
            "mesh_path": "/home/devel/.draft/renderformer/examples/templates/lighting/tri.obj",
            "transform": {
                "translation": [
                    0.0,
                    0.0,
                    2.1
                ],
                "rotation": [
                    0.0,
                    0.0,
                    0.0
                ],
                "scale": [
                    2.9732605043624103,
                    2.9732605043624103,
                    2.9732605043624103
                ],
                "normalize": false
            },
            "material": {
                "diffuse": [
                    1.0,
                    1.0,
                    1.0
                ],
                "specular": [
                    0.0,
                    0.0,
                    0.0
                ],
                "random_diffuse_max": 0.0,
                "roughness": 1.0,
                "emissive": [
                    6735.360234783713,
                    6735.360234783713,
                    6735.360234783713
                ],
                "smooth_shading": false,
                "rand_tri_diffuse_seed": null
            }
        }
    },
    "cameras": [
        {
            "position": [
                -0.7640546659159759,
                -2.768396301475139,
                0.44074274003950265
            ],
            "look_at": [
                0.0,
                0.0,
                0.0
            ],
            "up": [
                0.0,
                0.0,
                1.0
            ],
            "fov": 41.14427708090347
        }
    ]
}