{
    "scene_name": "random_scene_13_teapot",
    "version": "1.0",
    "objects": {
        "background_0": {
            "mesh_path": "examples/templates/backgrounds/plane.obj",
            "transform": {
                "translation": [
                    0.0,
                    0.0,
                    0.0
                ],
                "rotation": [
                    0.0,
                    0.0,
                    0.0
                ],
                "scale": [
                    0.5,
                    0.5,
                    0.5
                ],
                "normalize": false
            },
            "material": {
                "diffuse": [
                    0.2547389144582699,
                    0.2547389144582699,
                    0.2547389144582699
                ],
                "specular": [
                    0.01,
                    0.01,
                    0.01
                ],
                "random_diffuse_max": 0.4,
                "roughness": 0.99,
                "emissive": [
                    0.0,
                    0.0,
                    0.0
                ],
                "smooth_shading": true,
                "rand_tri_diffuse_seed": null,
                "random_diffuse_type": "per-triangle"
            },
            "remesh": false,
            "remesh_target_face_num": null
        },
        "background_1": {
            "mesh_path": "examples/templates/backgrounds/wall0.obj",
            "transform": {
                "translation": [
                    0.0,
                    0.0,
                    0.0
                ],
                "rotation": [
                    0.0,
                    0.0,
                    0.0
                ],
                "scale": [
                    0.5,
                    0.5,
                    0.5
                ],
                "normalize": false
            },
            "material": {
                "diffuse": [
                    0.28987314768982564,
                    0.28987314768982564,
                    0.28987314768982564
                ],
                "specular": [
                    0.01,
                    0.01,
                    0.01
                ],
                "random_diffuse_max": 0.4,
                "roughness": 0.99,
                "emissive": [
                    0.0,
                    0.0,
                    0.0
                ],
                "smooth_shading": true,
                "rand_tri_diffuse_seed": null,
                "random_diffuse_type": "per-triangle"
            },
            "remesh": false,
            "remesh_target_face_num": null
        },
        "background_2": {
            "mesh_path": "examples/templates/backgrounds/wall1.obj",
            "transform": {
                "translation": [
                    0.0,
                    0.0,
                    0.0
                ],
                "rotation": [
                    0.0,
                    0.0,
                    0.0
                ],
                "scale": [
                    0.5,
                    0.5,
                    0.5
                ],
                "normalize": false
            },
            "material": {
                "diffuse": [
                    0.3821495444925232,
                    0.47714133604118997,
                    0.6000246127927484
                ],
                "specular": [
                    0.01,
                    0.01,
                    0.01
                ],
                "random_diffuse_max": 0.4,
                "roughness": 0.99,
                "emissive": [
                    0.0,
                    0.0,
                    0.0
                ],
                "smooth_shading": true,
                "rand_tri_diffuse_seed": null,
                "random_diffuse_type": "per-triangle"
            },
            "remesh": false,
            "remesh_target_face_num": null
        },
        "background_3": {
            "mesh_path": "examples/templates/backgrounds/wall2.obj",
            "transform": {
                "translation": [
                    0.0,
                    0.0,
                    0.0
                ],
                "rotation": [
                    0.0,
                    0.0,
                    0.0
                ],
                "scale": [
                    0.5,
                    0.5,
                    0.5
                ],
                "normalize": false
            },
            "material": {
                "diffuse": [
                    0.3234231534053482,
                    0.1462740092553174,
                    0.48629512861778623
                ],
                "specular": [
                    0.01,
                    0.01,
                    0.01
                ],
                "random_diffuse_max": 0.4,
                "roughness": 0.99,
                "emissive": [
                    0.0,
                    0.0,
                    0.0
                ],
                "smooth_shading": true,
                "rand_tri_diffuse_seed": null,
                "random_diffuse_type": "per-triangle"
            },
            "remesh": false,
            "remesh_target_face_num": null
        },
        "teapot": {
            "mesh_path": "examples/objects/classical/teapot.obj",
            "transform": {
                "translation": [
                    0.3633733148904793,
                    0.13536267852997208,
                    -0.4893539939625656
                ],
                "rotation": [
                    198.03259313303244,
                    209.9114284819377,
                    4.349674463828421
                ],
                "scale": [
                    0.6987567153410172,
                    0.6987567153410172,
                    0.6987567153410172
                ],
                "normalize": true
            },
            "material": {
                "diffuse": [
                    0.461320001711803,
                    0.643485356925037,
                    0.42740009753223496
                ],
                "specular": [
                    0.9112708994463343,
                    0.9112708994463343,
                    0.9112708994463343
                ],
                "random_diffuse_max": 0.09321732551695394,
                "roughness": 0.1841817923022753,
                "emissive": [
                    0.0,
                    0.0,
                    0.0
                ],
                "smooth_shading": true,
                "rand_tri_diffuse_seed": null,
                "random_diffuse_type": "per-triangle"
            },
            "remesh": false,
            "remesh_target_face_num": null
        },
        "light_0": {
            "mesh_path": "examples/templates/lighting/tri.obj",
            "transform": {
                "translation": [
                    -0.4599453683747048,
                    0.5805892948840623,
                    2.140140569444463
                ],
                "rotation": [
                    0.0,
                    0.0,
                    0.0
                ],
                "scale": [
                    2.3580597770292897,
                    2.3580597770292897,
                    2.3580597770292897
                ],
                "normalize": false
            },
            "material": {
                "diffuse": [
                    1.0,
                    1.0,
                    1.0
                ],
                "specular": [
                    0.0,
                    0.0,
                    0.0
                ],
                "random_diffuse_max": 0.0,
                "roughness": 1.0,
                "emissive": [
                    4616.974666543319,
                    4616.974666543319,
                    4616.974666543319
                ],
                "smooth_shading": false,
                "rand_tri_diffuse_seed": null,
                "random_diffuse_type": "per-triangle"
            },
            "remesh": false,
            "remesh_target_face_num": null
        }
    },
    "cameras": [
        {
            "position": [
                1.2017081024685186,
                -2.009485388755648,
                0.028670623156149322
            ],
            "look_at": [
                0.0,
                0.0,
                0.0
            ],
            "up": [
                0.0,
                0.0,
                1.0
            ],
            "fov": 37.01217557014654
        }
    ]
}